<annotation>
	<folder>images</folder>
	<filename>12.png</filename>
	<path>E:\BaranovaOD\images\12.png</path>
	<source>
		<database>Unknown</database>
	</source>
	<size>
		<width>1921</width>
		<height>1441</height>
		<depth>3</depth>
	</size>
	<segmented>0</segmented>
	<object>
		<name>плансон</name>
		<pose>Unspecified</pose>
		<truncated>0</truncated>
		<difficult>0</difficult>
		<bndbox>
			<xmin>733</xmin>
			<ymin>392</ymin>
			<xmax>1330</xmax>
			<ymax>1075</ymax>
		</bndbox>
	</object>
	<object>
		<name>повреждение</name>
		<pose>Unspecified</pose>
		<truncated>0</truncated>
		<difficult>0</difficult>
		<bndbox>
			<xmin>849</xmin>
			<ymin>716</ymin>
			<xmax>931</xmax>
			<ymax>784</ymax>
		</bndbox>
	</object>
</annotation>
